docbuilder.py
docbuilder-0.5.data/scripts/docbuilder.py
docbuilder-0.5.dist-info/DESCRIPTION.rst
docbuilder-0.5.dist-info/METADATA
docbuilder-0.5.dist-info/metadata.json
docbuilder-0.5.dist-info/RECORD
docbuilder-0.5.dist-info/top_level.txt
docbuilder-0.5.dist-info/WHEEL
